testrail_data_model/__init__.py
testrail_data_model/adapter.py
testrail_data_model/builder.py
testrail_data_model/deletion.py
testrail_data_model/model.py
testrail_data_model/singleton.py
testrail_data_model/stats.py
testrail_data_model-0.2.0.dist-info/LICENSE
testrail_data_model-0.2.0.dist-info/METADATA
testrail_data_model-0.2.0.dist-info/WHEEL
testrail_data_model-0.2.0.dist-info/top_level.txt
testrail_data_model-0.2.0.dist-info/RECORD
