Metadata-Version: 2.1
Name: testrail-data-model
Version: 0.2.0
Summary: Package for creating and managing objects from the TestRail API
Home-page: https://github.com/PandoraMedia/testrail-data-model
Author: Elliot Weiser
Author-email: elliot.weiser@gmail.com
License: UNKNOWN
Keywords: testrail,testrail-api,api,testrail-client,client,testrail-objects,objects
Platform: any
Classifier: Intended Audience :: Developers
Classifier: Natural Language :: English
Classifier: Operating System :: OS Independent
Classifier: Programming Language :: Python
Classifier: Programming Language :: Python :: 3.8
Classifier: Programming Language :: Python :: 3.9
Classifier: Programming Language :: Python :: 3.10
Classifier: Programming Language :: Python :: Implementation :: CPython
Classifier: Programming Language :: Python :: Implementation :: PyPy
Classifier: Topic :: Software Development :: Libraries :: Python Modules
Requires-Python: >=3.8
License-File: LICENSE
